unified_json_api/__init__.py
unified_json_api/constants_unified_json.py
unified_json_api/unified_json.py
unified_json_api-0.0.11.dist-info/METADATA
unified_json_api-0.0.11.dist-info/WHEEL
unified_json_api-0.0.11.dist-info/top_level.txt
unified_json_api-0.0.11.dist-info/RECORD
